alignak_module_backend/__init__.py
alignak_module_backend/arbiter/__init__.py
alignak_module_backend/arbiter/module.py
alignak_module_backend/broker/__init__.py
alignak_module_backend/broker/module.py
alignak_module_backend/etc/__init__.py
alignak_module_backend/etc/alignak.d/backend-arbiter.ini
alignak_module_backend/etc/alignak.d/backend-broker.ini
alignak_module_backend/etc/alignak.d/backend-scheduler.ini
alignak_module_backend/scheduler/__init__.py
alignak_module_backend/scheduler/module.py
alignak_module_backend-1.4.3.data/data/share/alignak/etc/alignak.d/backend-arbiter.ini
alignak_module_backend-1.4.3.data/data/share/alignak/etc/alignak.d/backend-broker.ini
alignak_module_backend-1.4.3.data/data/share/alignak/etc/alignak.d/backend-scheduler.ini
alignak_module_backend-1.4.3.dist-info/METADATA
alignak_module_backend-1.4.3.dist-info/RECORD
alignak_module_backend-1.4.3.dist-info/WHEEL
alignak_module_backend-1.4.3.dist-info/top_level.txt
