Metadata-Version: 2.1
Name: alignak-module-backend
Version: 1.4.3
Summary: Alignak - Backend modules for Arbiter, Scheduler and Broker
Home-page: https://github.com/Alignak-monitoring-contrib/alignak-module-backend
Author: David Durieux
Author-email: david.durieux@alignak.net
License: GNU Affero General Public License, version 3
Keywords: alignak monitoring module backend
Platform: UNKNOWN
Classifier: Development Status :: 5 - Production/Stable
Classifier: Environment :: Console
Classifier: Intended Audience :: Developers
Classifier: Intended Audience :: System Administrators
Classifier: License :: OSI Approved :: GNU Affero General Public License v3 or later (AGPLv3+)
Classifier: Natural Language :: English
Classifier: Programming Language :: Python
Classifier: Topic :: System :: Monitoring
Classifier: Topic :: System :: Systems Administration
Requires-Dist: six
Requires-Dist: alignak-backend-client
